[
	{
		"$schema": "@schemas/sql-json-schema.json#",
		"version": "10.1.1040",
		"outputFile": "SqlScripts/application.sql",
		"inputFiles": [
			"@sql/platform/a2v10minimal.sql",
			"main/_sql/common/security_common.sql",
			"main/_sql/security.sql",
			"main/_sql/struct.sql",
			"main/_sql/migrations.sql",
			"main/_sql/common.sql",
			"main/_sql/ui.sql",
			"main/profile/default/default.sql",
			"main/settings/policy/policy.sql",
			"main/catalog/tag/tag.sql",
			"main/catalog/company/company.sql",
			"main/catalog/warehouse/warehouse.sql",
			"main/catalog/item/item.sql",
			"main/catalog/item/variant.sql",
			"main/catalog/itemgroup/groupitem.sql",
			"main/catalog/itemoption/itemoption.sql",
			"main/catalog/account/account.sql",
			"main/catalog/agent/agent.sql",
			"main/catalog/person/person.sql",
			"main/catalog/contract/contract.sql",
			"main/catalog/contact/contact.sql",
			"main/catalog/bank/bank.sql",
			"main/catalog/country/country.sql",
			"main/catalog/bankaccount/bankaccount.sql",
			"main/catalog/cashaccount/cashaccount.sql",
			"main/catalog/acckind/acckind.sql",
			"main/catalog/itemrole/itemrole.sql",
			"main/catalog/unit/unit.sql",
			"main/catalog/vendor/vendor.sql",
			"main/catalog/brand/brand.sql",
			"main/catalog/currency/currency.sql",
			"main/catalog/pricekind/pricekind.sql",
			"main/catalog/cashflowitem/cashflowitem.sql",
			"main/catalog/costitem/costitem.sql",
			"main/catalog/project/project.sql",
			"main/catalog/respcenter/respcenter.sql",
			"main/catalog/autonum/autonum.sql",
			"main/catalog/docstate/docstate.sql",
			"main/catalog/crm/leadstage/leadstage.sql",
			"main/dashboard/dashboard.sql",
			"main/accounting/plan/plan.sql",
			"main/settings/accountplan/plan.sql",
			"main/settings/operation/operation.sql",
			"main/document/document.common.sql",
			"main/document/document.stock.sql",
			"main/document/document.pay.sql",
			"main/document/document.order.sql",
			"main/document/document.apply.sql",
			"main/document/document.dialogs.sql",
			"main/document/document.commands.sql",
			"main/document/print/print.sql",
			"main/sales/price/price.sql",
			"main/crm/lead/lead.sql",
			"main/task/partial/partial.sql",
			"main/reports/report.sql",
			"main/reports/stock/report.stock.sql",
			"main/reports/agent/report.agent.sql",
			"main/reports/account/report.account.sql",
			"main/reports/plan/report.plan.sql",
			"main/reports/cash/report.cash.sql",
			"main/reports/settle/report.settle.sql",
			"main/settings/develop/develop.sql",
			"main/settings/develop/application.sql",
			"main/settings/integration/integration.sql",
			"main/settings/user/user.sql",
			"main/sales/widgets/widgets.sql",
			"main/_navpane/navpane.sql",
			"main/_sql/admin.sql",
			"main/_sql/initial_catalog.sql",
			"main/_sql/initial_data.sql",
			"main/_sql/flush.sql"
		]
	},
	{
		"version": "10.1.1040",
		"outputFile": "SqlScripts/catalog.sql",
		"inputFiles": [
			"main/_sql/common/security_common.sql",
			"main/_sql/catalog/catalog_security.sql",
			"main/_sql/catalog/catalog_ui.sql"
		]
	},
	{
		"version": "10.1.1040",
		"outputFile": "SqlScripts/multitenant.sql",
		"inputFiles": [
			"main/_sql/startup_mt.sql"
		]
	},
	{
		"version": "10.1.1040",
		"outputFile": "SqlScripts/manufacturing.sql",
		"inputFiles": [
			"manufacturing/_sql/ui.sql"
		]
	}
]
